neutronpy/__init__.py
neutronpy/constants.py
neutronpy/crystal/__init__.py
neutronpy/crystal/atom.py
neutronpy/crystal/lattice.py
neutronpy/crystal/material.py
neutronpy/crystal/plot.py
neutronpy/crystal/sample.py
neutronpy/crystal/structure_factors.py
neutronpy/crystal/symmetry.py
neutronpy/crystal/tools.py
neutronpy/data/__init__.py
neutronpy/data/analysis.py
neutronpy/data/data.py
neutronpy/data/plot.py
neutronpy/data/scans.py
neutronpy/database/magnetic_form_factors.json
neutronpy/database/periodic_table.json
neutronpy/database/scattering_lengths.json
neutronpy/database/symmetry.json
neutronpy/energy.py
neutronpy/exceptions.py
neutronpy/fileio/__init__.py
neutronpy/fileio/data.py
neutronpy/fileio/instrument.py
neutronpy/fileio/loaders/__init__.py
neutronpy/fileio/loaders/dcs_mslice.py
neutronpy/fileio/loaders/grasp.py
neutronpy/fileio/loaders/ice.py
neutronpy/fileio/loaders/icp.py
neutronpy/fileio/loaders/mad.py
neutronpy/fileio/loaders/neutronpy.py
neutronpy/fileio/loaders/spice.py
neutronpy/fileio/material.py
neutronpy/fileio/sample.py
neutronpy/functions.py
neutronpy/gui.py
neutronpy/instrument/__init__.py
neutronpy/instrument/analyzer.py
neutronpy/instrument/chopper.py
neutronpy/instrument/detector.py
neutronpy/instrument/exceptions.py
neutronpy/instrument/general.py
neutronpy/instrument/goniometer.py
neutronpy/instrument/guide.py
neutronpy/instrument/instrument.py
neutronpy/instrument/monochromator.py
neutronpy/instrument/plot.py
neutronpy/instrument/takin.py
neutronpy/instrument/tas_instrument.py
neutronpy/instrument/tof_instrument.py
neutronpy/instrument/tools.py
neutronpy/logger.py
neutronpy/lsfit/__init__.py
neutronpy/lsfit/fitter.py
neutronpy/lsfit/plot.py
neutronpy/lsfit/tools.py
neutronpy/models.py
neutronpy/scattering/__init__.py
neutronpy/scattering/pattern.py
neutronpy/scattering/polarimetry.py
neutronpy/scattering/polarization.py
neutronpy/spurion.py
neutronpy/ui/resolution.ui
neutronpy-2.0.0.dist-info/entry_points.txt
neutronpy-2.0.0.dist-info/LICENSE.txt
neutronpy-2.0.0.dist-info/LICENSE.RESLIB.txt
neutronpy-2.0.0.dist-info/WHEEL
neutronpy-2.0.0.dist-info/METADATA
neutronpy-2.0.0.dist-info/RECORD
