Metadata-Version: 2.1
Name: neutronpy
Version: 2.0.0
Summary: NeutronPy is a collection of commonly used tools aimed at facilitating the analysis of neutron scattering data. NeutronPy is built primarily using the numpy and scipy python libraries, with a translation of ResLib 3.4c (MatLab) routines for Instrument resolution calculations.
License: MIT
Author: David M Fobes
Author-email: dfobes@lanl.gov
Requires-Python: >=3.6,<4.0
Classifier: License :: OSI Approved :: MIT License
Classifier: Programming Language :: Python :: 3
Classifier: Programming Language :: Python :: 3.6
Classifier: Programming Language :: Python :: 3.7
Classifier: Programming Language :: Python :: 3.8
Classifier: Programming Language :: Python :: 3.9
Requires-Dist: h5py (>=3.1.0,<4.0.0)
Requires-Dist: lmfit (>=0.9.5,<0.10.0)
Requires-Dist: matplotlib (>=2.0,<3.0)
Requires-Dist: numpy (>=1.10,<2.0)
Requires-Dist: scipy (>=1.0,<2.0)
